spacytei/__init__.py
spacytei/config.py
spacytei/conversion.py
spacytei/data_loaders.py
spacytei/data_prep.py
spacytei/doccano.py
spacytei/eval.py
spacytei/ner.py
spacytei/pipeline.py
spacytei/prodigy.py
spacytei/recogito.py
spacytei/tcf.py
spacytei/tei.py
spacytei/tei_process.py
spacytei/tfc.py
spacytei/tokenlist.py
spacytei/train.py
spacytei/vecs.py
spacytei/xml.py
spacytei/schema/__init__.py
spacytei/schema/acdh_json_example.json
spacytei/schema/acdh_lang_jsonschema.json
spacytei/schema/acdh_tokeneditor_schema.py
spacytei/schema/tei_all.xsd
acdh_spacytei-0.1.2.dist-info/LICENSE.txt
acdh_spacytei-0.1.2.dist-info/METADATA
acdh_spacytei-0.1.2.dist-info/WHEEL
acdh_spacytei-0.1.2.dist-info/top_level.txt
acdh_spacytei-0.1.2.dist-info/RECORD
