Metadata-Version: 2.1
Name: acdh-spacytei
Version: 0.1.2
Summary: A package to ease processing (not only) TEI documents with spaCy
Home-page: https://github.com/acdh-oeaw/acdh-spacytei
Author: Peter Andorfer, Matthias Schlögl, Saranya Balasubramanian
Author-email: matthias.schloegl@oeaw.ac.at, peter.andorfer@oeaw.ac.at, saranya.balasubramanian@oeaw.ac.at
License: MIT
Platform: UNKNOWN
Classifier: Development Status :: 3 - Alpha
Classifier: Intended Audience :: Developers
Classifier: License :: OSI Approved :: BSD License
Classifier: Natural Language :: English
Classifier: Programming Language :: Python :: 3
Classifier: Programming Language :: Python :: 3.4
Classifier: Programming Language :: Python :: 3.5
Classifier: Programming Language :: Python :: 3.6
Requires-Dist: spacy (>=2.1.4)
Requires-Dist: scikit-learn (>=0.20.2)
Requires-Dist: gensim (>=3.7.1)
Requires-Dist: lxml (>=4.1.1)
Requires-Dist: pandas (>=0.23.3)
Requires-Dist: requests (>=2.20.1)
Requires-Dist: langid (>=1.1.6)
Requires-Dist: jsonschema (>=3.0.0)
